{"classList":[ { "id": "53e33542f8295b2e57db3c13", "className": "Paige Wagner", "catalogList": [ { "id": 0, "catalogName": "Kelly Mcgee" }, { "id": 1, "catalogName": "Johanna Parrish" }, { "id": 2, "catalogName": "Davis Santos" }, { "id": 3, "catalogName": "Lawrence Figueroa" }, { "id": 4, "catalogName": "Amanda Mclean" }, { "id": 5, "catalogName": "Wright Snider" }, { "id": 6, "catalogName": "Fitzpatrick Reeves" }, { "id": 7, "catalogName": "Georgette Pratt" }, { "id": 8, "catalogName": "Hooper Harper" } ] }, { "id": "53e335423a70e5b8a28d8060", "className": "Margery Gill", "catalogList": [ { "id": 0, "catalogName": "Britt Oliver" }, { "id": 1, "catalogName": "Flowers Cabrera" }, { "id": 2, "catalogName": "Angelina Tucker" }, { "id": 3, "catalogName": "Price Ellis" }, { "id": 4, "catalogName": "Underwood Parks" } ] }, { "id": "53e3354218aab87822d1c889", "className": "Holmes Burks", "catalogList": [ { "id": 0, "catalogName": "Traci Bryant" }, { "id": 1, "catalogName": "Mcbride Finch" }, { "id": 2, "catalogName": "Elma Woods" }, { "id": 3, "catalogName": "Swanson Whitfield" }, { "id": 4, "catalogName": "Charles Bowman" }, { "id": 5, "catalogName": "Cole Howe" }, { "id": 6, "catalogName": "Hart Donaldson" }, { "id": 7, "catalogName": "Lori Miller" } ] }, { "id": "53e33542304bc42b8526f36e", "className": "Dodson Henry", "catalogList": [ { "id": 0, "catalogName": "Kenya Barrett" }, { "id": 1, "catalogName": "Cannon Bishop" }, { "id": 2, "catalogName": "Justine Hunt" }, { "id": 3, "catalogName": "Wendi Heath" }, { "id": 4, "catalogName": "Caldwell Mcdowell" }, { "id": 5, "catalogName": "Tyson Hurst" }, { "id": 6, "catalogName": "Frank Sherman" }, { "id": 7, "catalogName": "Shana Odom" } ] }, { "id": "53e3354274968d0782ff8a53", "className": "Hardy Holland", "catalogList": [ { "id": 0, "catalogName": "Haney Rodriquez" }, { "id": 1, "catalogName": "Nanette Kelly" }, { "id": 2, "catalogName": "Tabatha Ramirez" }, { "id": 3, "catalogName": "Barrett Mullen" }, { "id": 4, "catalogName": "Carlson Caldwell" }, { "id": 5, "catalogName": "Lenora Mcclain" }, { "id": 6, "catalogName": "Newman Brooks" }, { "id": 7, "catalogName": "Nadia Greene" } ] }, { "id": "53e335422e982ab1844b144e", "className": "Erickson Mack", "catalogList": [ { "id": 0, "catalogName": "Lang Moreno" }, { "id": 1, "catalogName": "Jacklyn Dorsey" }, { "id": 2, "catalogName": "Burch Jensen" }, { "id": 3, "catalogName": "Foley Webb" }, { "id": 4, "catalogName": "Chandler Swanson" }, { "id": 5, "catalogName": "Mitchell Le" }, { "id": 6, "catalogName": "Marissa Lawrence" } ] }, { "id": "53e33542a68eda667ed8994d", "className": "Marla Howell", "catalogList": [ { "id": 0, "catalogName": "Hill Benson" }, { "id": 1, "catalogName": "Genevieve Little" }, { "id": 2, "catalogName": "Jaclyn Mayo" }, { "id": 3, "catalogName": "Alexandra Gay" }, { "id": 4, "catalogName": "Ladonna Merritt" }, { "id": 5, "catalogName": "Colleen Orr" }, { "id": 6, "catalogName": "Oneill Duncan" }, { "id": 7, "catalogName": "Gay Parker" } ] }, { "id": "53e335421d5ba37c27044cbc", "className": "Linda Oneal", "catalogList": [ { "id": 0, "catalogName": "Goodwin Battle" }, { "id": 1, "catalogName": "Jeanie Berger" }, { "id": 2, "catalogName": "Holly Sexton" } ] } ] }